{
  "friends" : [
    {
      "site" : "https:\/\/ddark.ws\/",
      "name" : "ddark-il",
      "photo" : "friends\/918A0FA5-7C31-42D0-85F9-46D88BB273F1\/profile.jpg"
    }
  ],
  "profile_pic" : "profile.jpg",
  "name" : "ddark-il",
  "bio" : "Manically depressed robot ",
  "posts" : [
    {
      "date" : 1744898507,
      "title" : "Photos from Midbarium",
      "id" : "D2157FB8-A15E-426E-8823-87AAC7FDC205",
      "photos" : [
        {
          "exif" : {
            "Model" : "LEICA Q2",
            "DateTimeOriginal" : "2025:03:15 14:51:54",
            "iso" : "100",
            "fstop" : "f\/4.5",
            "shutter" : "1\/250",
            "Make" : "LEICA CAMERA AG"
          },
          "path" : "photos\/D2157FB8-A15E-426E-8823-87AAC7FDC205\/photo_0.jpg"
        },
        {
          "exif" : {
            "fstop" : "f\/5.6",
            "iso" : "100",
            "DateTimeOriginal" : "2025:03:15 15:15:33",
            "Make" : "LEICA CAMERA AG",
            "Model" : "LEICA Q2",
            "shutter" : "1\/500"
          },
          "path" : "photos\/D2157FB8-A15E-426E-8823-87AAC7FDC205\/photo_1.jpg"
        },
        {
          "path" : "photos\/D2157FB8-A15E-426E-8823-87AAC7FDC205\/photo_2.jpg",
          "exif" : {
            "Model" : "LEICA Q2",
            "fstop" : "f\/2.2",
            "Make" : "LEICA CAMERA AG",
            "iso" : "100",
            "DateTimeOriginal" : "2025:03:15 15:08:51",
            "shutter" : "1\/60"
          }
        },
        {
          "path" : "photos\/D2157FB8-A15E-426E-8823-87AAC7FDC205\/photo_3.jpg",
          "exif" : {
            "iso" : "100",
            "DateTimeOriginal" : "2025:03:15 14:24:36",
            "shutter" : "1\/400",
            "Make" : "LEICA CAMERA AG",
            "Model" : "LEICA Q2",
            "fstop" : "f\/5.0"
          }
        },
        {
          "exif" : {
            "shutter" : "1\/160",
            "fstop" : "f\/4.0",
            "DateTimeOriginal" : "2025:03:15 15:27:04",
            "iso" : "100",
            "Make" : "LEICA CAMERA AG",
            "Model" : "LEICA Q2"
          },
          "path" : "photos\/D2157FB8-A15E-426E-8823-87AAC7FDC205\/photo_4.jpg"
        },
        {
          "exif" : {
            "Make" : "LEICA CAMERA AG",
            "fstop" : "f\/4.0",
            "shutter" : "1\/200",
            "iso" : "100",
            "Model" : "LEICA Q2",
            "DateTimeOriginal" : "2025:03:15 16:22:07"
          },
          "path" : "photos\/D2157FB8-A15E-426E-8823-87AAC7FDC205\/photo_5.jpg"
        }
      ],
      "description" : "New Zoo in Beer Sheva",
      "album" : "Travel"
    },
    {
      "title" : "Larnaca",
      "description" : "Short trip to Larnaca, Cyprus",
      "album" : "Travel",
      "id" : "BEE8A350-C372-4A61-98CD-EE7F4BDBF6D7",
      "date" : 1745054426,
      "photos" : [
        {
          "exif" : {
            "DateTimeOriginal" : "2025:04:04 10:04:38",
            "Model" : "LEICA Q2",
            "Make" : "LEICA CAMERA AG",
            "fstop" : "f\/6.3",
            "shutter" : "1\/1250",
            "iso" : "100"
          },
          "path" : "photos\/BEE8A350-C372-4A61-98CD-EE7F4BDBF6D7\/photo_0.jpg"
        },
        {
          "exif" : {
            "fstop" : "f\/5.6",
            "shutter" : "1\/1000",
            "Model" : "LEICA Q2",
            "iso" : "100",
            "DateTimeOriginal" : "2025:04:04 10:21:06",
            "Make" : "LEICA CAMERA AG"
          },
          "path" : "photos\/BEE8A350-C372-4A61-98CD-EE7F4BDBF6D7\/photo_1.jpg"
        },
        {
          "path" : "photos\/BEE8A350-C372-4A61-98CD-EE7F4BDBF6D7\/photo_2.jpg",
          "exif" : {
            "DateTimeOriginal" : "2025:04:04 10:10:49",
            "fstop" : "f\/1.7",
            "Model" : "LEICA Q2",
            "iso" : "1000",
            "Make" : "LEICA CAMERA AG",
            "shutter" : "1\/50"
          }
        },
        {
          "path" : "photos\/BEE8A350-C372-4A61-98CD-EE7F4BDBF6D7\/photo_3.jpg",
          "exif" : {
            "fstop" : "f\/1.7",
            "shutter" : "1\/50",
            "iso" : "200",
            "Make" : "LEICA CAMERA AG",
            "DateTimeOriginal" : "2025:04:04 10:08:16",
            "Model" : "LEICA Q2"
          }
        },
        {
          "path" : "photos\/BEE8A350-C372-4A61-98CD-EE7F4BDBF6D7\/photo_4.jpg",
          "exif" : {
            "DateTimeOriginal" : "2025:04:04 10:37:28",
            "shutter" : "1\/1000",
            "iso" : "100",
            "fstop" : "f\/6.3",
            "Model" : "LEICA Q2",
            "Make" : "LEICA CAMERA AG"
          }
        },
        {
          "exif" : {
            "iso" : "100",
            "Model" : "LEICA Q2",
            "shutter" : "1\/800",
            "DateTimeOriginal" : "2025:04:04 10:40:34",
            "Make" : "LEICA CAMERA AG",
            "fstop" : "f\/5.6"
          },
          "path" : "photos\/BEE8A350-C372-4A61-98CD-EE7F4BDBF6D7\/photo_5.jpg"
        },
        {
          "path" : "photos\/BEE8A350-C372-4A61-98CD-EE7F4BDBF6D7\/photo_6.jpg",
          "exif" : {
            "DateTimeOriginal" : "2025:04:05 08:55:21",
            "iso" : "100",
            "shutter" : "1\/800",
            "fstop" : "f\/5.6",
            "Make" : "LEICA CAMERA AG",
            "Model" : "LEICA Q2"
          }
        },
        {
          "path" : "photos\/BEE8A350-C372-4A61-98CD-EE7F4BDBF6D7\/photo_7.jpg",
          "exif" : {
            "fstop" : "f\/5.6",
            "Make" : "LEICA CAMERA AG",
            "shutter" : "1\/1000",
            "DateTimeOriginal" : "2025:04:05 09:11:06",
            "iso" : "100",
            "Model" : "LEICA Q2"
          }
        },
        {
          "path" : "photos\/BEE8A350-C372-4A61-98CD-EE7F4BDBF6D7\/photo_8.jpg",
          "exif" : {
            "Make" : "LEICA CAMERA AG",
            "iso" : "100",
            "DateTimeOriginal" : "2025:04:05 09:45:38",
            "fstop" : "f\/5.6",
            "shutter" : "1\/1000",
            "Model" : "LEICA Q2"
          }
        },
        {
          "path" : "photos\/BEE8A350-C372-4A61-98CD-EE7F4BDBF6D7\/photo_9.jpg",
          "exif" : {
            "Make" : "LEICA CAMERA AG",
            "Model" : "LEICA Q2",
            "iso" : "100",
            "DateTimeOriginal" : "2025:04:05 11:21:18",
            "fstop" : "f\/4.0",
            "shutter" : "1\/160"
          }
        }
      ]
    }
  ]
}